dataland/__init__.py
dataland/_meta.py
dataland/base.py
dataland/gcloud/README.md
dataland/gcloud/__init__.py
dataland/gcloud/bigquery/__init__.py
dataland/gcloud/bigquery/base.py
dataland/gcloud/dataproc/__init__.py
dataland/gcloud/dataproc/_data.py
dataland/gcloud/dataproc/api.py
dataland/gcloud/storage/__init__.py
dataland/gcloud/storage/base.py
dataland/nlp/__init__.py
dataland/nlp/_string.py
dataland/nlp/utils.py
dataland/spark.py
dataland/utils.py
dataland-0.1.7.dist-info/LICENSE
dataland-0.1.7.dist-info/WHEEL
dataland-0.1.7.dist-info/METADATA
dataland-0.1.7.dist-info/RECORD
